what2_regex-0.1.2.dist-info/METADATA
what2_regex-0.1.2.dist-info/WHEEL
what2_regex-0.1.2.dist-info/entry_points.txt
what2_regex-0.1.2.dist-info/licenses/LICENSE
what2_regex/__init__.py
what2_regex/py.typed
what2_regex/w2.py
what2_regex-0.1.2.dist-info/RECORD
