Metadata-Version: 2.1
Name: what2-regex
Version: 0.1.2
Summary: What2 Regex
Author-Email: Marc Edwards <marc@mlwhat.com>
License: MIT
Classifier: Development Status :: 3 - Alpha
Project-URL: Homepage, https://github.com/alwaysmpe/what2_regex
Project-URL: Repository, https://github.com/alwaysmpe/what2_regex
Requires-Python: >=3.13
